cloudshell/__init__.py
cloudshell/helpers/__init__.py
cloudshell/helpers/sandbox_reporter/__init__.py
cloudshell/helpers/sandbox_reporter/html_wrap.py
cloudshell/helpers/sandbox_reporter/reporter.py
cloudshell/helpers/sandbox_reporter/sandbox_console.py
cloudshell_sandbox_reporter-0.1.1.dist-info/LICENSE
cloudshell_sandbox_reporter-0.1.1.dist-info/METADATA
cloudshell_sandbox_reporter-0.1.1.dist-info/WHEEL
cloudshell_sandbox_reporter-0.1.1.dist-info/top_level.txt
cloudshell_sandbox_reporter-0.1.1.dist-info/RECORD
