Metadata-Version: 2.1
Name: cloudshell-sandbox-reporter
Version: 0.1.1
Summary: Helper modules and classes for writing to Cloudshell sandbox console
Home-page: https://github.com/QualiSystemsLab/cloudshell-sandbox-reporter
Author: QualiLab
Author-email: support@qualisystems.com
License: MIT
Classifier: Programming Language :: Python :: 3.7
Classifier: License :: OSI Approved :: MIT License
Classifier: Operating System :: OS Independent
Requires-Python: >=3.7
License-File: LICENSE
Requires-Dist: cloudshell-automation-api
